cryptofetch/__init__.py
cryptofetch/__main__.py
cryptofetch/fetcher.py
cryptofetch-1.2.2.dist-info/LICENSE
cryptofetch-1.2.2.dist-info/METADATA
cryptofetch-1.2.2.dist-info/WHEEL
cryptofetch-1.2.2.dist-info/entry_points.txt
cryptofetch-1.2.2.dist-info/top_level.txt
cryptofetch-1.2.2.dist-info/RECORD
