Metadata-Version: 2.1
Name: cryptofetch
Version: 1.2.2
Summary: CLI tool to fetch and view cryptocurrencies prices
Home-page: https://github.com/codeswhite/cryptofetch
Author: Max G
Author-email: max3227@gmail.com
License: UNKNOWN
Platform: UNKNOWN
Classifier: Programming Language :: Python :: 3
Classifier: License :: OSI Approved :: MIT License
Classifier: Operating System :: OS Independent
Requires-Python: >=3.8
Requires-Dist: interutils
Requires-Dist: prettytable
Requires-Dist: requests
